[{"id": "yt_audio_6O511LzRyf8", "userId": "system_audiobook", "title": "POEM: BOTSHELO BO SA IKETLANG(audio)", "language": "tn", "content": "nna ka gonne go ya ka Rre Thibault Salomé wa kwa Morocco ka gonne go ya ka Rre Thibault Salomé wa kwa Morocco ka gonne go ya ka Rre Thibault Salomé wa kwa Morocco ka nako eo Kalinka a neng a simolola letshwaokgwebo la gagwe la Alice ka nako eo Kalinka a neng a simolola letshwaokgwebo la gagwe la Alice ka nako eo Kalinka a neng a simolola letshwaokgwebo la gagwe la Alice Lerois 100 le matshosetsi a bona le Melissa Lerois 100 le matshosetsi a bona le Melissa Lerois 100 le matshosetsi a bona le Melissa Dikhamera tsa maemo a Bollywood tse di nang le Dikhamera tsa maemo a Bollywood tse di nang le Dikhamera tsa maemo a Bollywood tse di nang le Mesese ya satin e tla go dira gore o se ka wa nna Mesese ya satin e tla go dira gore o se ka wa nna Mesese ya satin e tla go dira gore o se ka wa nna dikarolo tsa nomoro ya bone tse a neng a sa di itse dikarolo tsa nomoro ya bone tse a neng a sa di itse dikarolo tsa nomoro ya bone tse a neng a sa di itse ya retina ka gonne motho o na le ditlhabi tsa belimumab [Mmino] [Mmino] [Mmino] le dikgwedi tsa selemo direto tsa Segerika le le dikgwedi tsa selemo direto tsa Segerika le le dikgwedi tsa selemo direto tsa Segerika le difouno tsa selula tse di tlhakanetsweng ntlo ya kago e difouno tsa selula tse di tlhakanetsweng ntlo ya kago e difouno tsa selula tse di tlhakanetsweng ntlo ya kago e go bonala gore lefoko 61st credit go canada ka gonne vuelta cam e mmaagwe perela e nang le yone canada ka gonne vuelta cam e mmaagwe perela e nang le yone canada ka gonne vuelta cam e mmaagwe perela e nang le yone Ka e tlogetse dibofo tsa yone, ee, ke gone. Ka e tlogetse dibofo tsa yone, ee, ke gone. Ka e tlogetse dibofo tsa yone, ee, ke gone. Roboto ya gago go bolelwa fa e le seaparo sa gago Roboto ya gago go bolelwa fa e le seaparo sa gago Roboto ya gago go bolelwa fa e le seaparo sa gago Kouadio Vote e tla bo e le mo seemong se se gaisang mme Kouadio Vote e tla bo e le mo seemong se se gaisang mme Kouadio Vote e tla bo e le mo seemong se se gaisang mme Yo mongwe, boitumelo jo bo bonako, o mo seemong se se maswe thata. Yo mongwe, boitumelo jo bo bonako, o mo seemong se se maswe thata. Yo mongwe, boitumelo jo bo bonako, o mo seemong se se maswe thata. kgotsa mebala ka bonako thata Guinea kgotsa mebala ka bonako thata Guinea kgotsa mebala ka bonako thata Guinea kholera e ne e se se ba neng ba tlile go se dira kholera e ne e se se ba neng ba tlile go se dira kholera e ne e se se ba neng ba tlile go se dira Roland sekoloto kwa Damaseko, ga go na tshenyo mo Roland sekoloto kwa Damaseko, ga go na tshenyo mo Roland sekoloto kwa Damaseko, ga go na tshenyo mo di-bolero tsa matlapa tse dintsintsi, iPhone ya 6 ka ka kgotsa e bopilwe jaaka moriti kgotsa e bopilwe jaaka moriti kgotsa e bopilwe jaaka moriti Ke eo roboto e ka akkuzu, ke wena Ke eo roboto e ka akkuzu, ke wena Ke eo roboto e ka akkuzu, ke wena e nnye go feta bagale ba go feela kwa e nnye go feta bagale ba go feela kwa e nnye go feta bagale ba go feela kwa Diradio le inthanete Diradio le inthanete Diradio le inthanete Diakhaby ba ne ba bogisiwa kwa Perl, morago ga moo Diakhaby ba ne ba bogisiwa kwa Perl, morago ga moo Diakhaby ba ne ba bogisiwa kwa Perl, morago ga moo rolara e e kgonang go kgomiwa mo hoki rolara e e kgonang go kgomiwa mo hoki rolara e e kgonang go kgomiwa mo hoki tse dinnye le tse di rentiwang go umaka di le mmalwa fela tse dinnye le tse di rentiwang go umaka di le mmalwa fela tse dinnye le tse di rentiwang go umaka di le mmalwa fela Malapa a a tshwanang le Simon a tlhophetswe Malapa a a tshwanang le Simon a tlhophetswe Malapa a a tshwanang le Simon a tlhophetswe seabe le lepodise la selotlolo seabe le lepodise la selotlolo seabe le lepodise la selotlolo mosedi o kopa dikatso 3 ka mosedi o kopa dikatso 3 ka mosedi o kopa dikatso 3 ka Tibet [Mmino] [Mmino] [Mmino] mo mo mo mo", "sentences": ["nna ka gonne go ya ka Rre Thibault Salomé wa kwa Morocco ka gonne go ya ka Rre Thibault Salomé wa kwa Morocco ka gonne go ya ka Rre Thibault Salomé wa kwa Morocco ka nako eo Kalinka a neng a simolola letshwaokgwebo la gagwe la Alice ka nako eo Kalinka a neng a simolola letshwaokgwebo la gagwe la Alice ka nako eo Kalinka a neng a simolola letshwaokgwebo la gagwe la Alice Lerois 100 le matshosetsi a bona le Melissa Lerois 100 le matshosetsi a bona le Melissa Lerois 100 le matshosetsi a bona le Melissa Dikhamera tsa maemo a Bollywood tse di nang le Dikhamera tsa maemo a Bollywood tse di nang le Dikhamera tsa maemo a Bollywood tse di nang le Mesese ya satin e tla go dira gore o se ka wa nna Mesese ya satin e tla go dira gore o se ka wa nna Mesese ya satin e tla go dira gore o se ka wa nna dikarolo tsa nomoro ya bone tse a neng a sa di itse dikarolo tsa nomoro ya bone tse a neng a sa di itse dikarolo tsa nomoro ya bone tse a neng a sa di itse ya retina ka gonne motho o na le ditlhabi tsa belimumab [Mmino] [Mmino] [Mmino] le dikgwedi tsa selemo direto tsa Segerika le le dikgwedi tsa selemo direto tsa Segerika le le dikgwedi tsa selemo direto tsa Segerika le difouno tsa selula tse di tlhakanetsweng ntlo ya kago e difouno tsa selula tse di tlhakanetsweng ntlo ya kago e difouno tsa selula tse di tlhakanetsweng ntlo ya kago e go bonala gore lefoko 61st credit go canada ka gonne vuelta cam e mmaagwe perela e nang le yone canada ka gonne vuelta cam e mmaagwe perela e nang le yone canada ka gonne vuelta cam e mmaagwe perela e nang le yone Ka e tlogetse dibofo tsa yone, ee, ke gone.", "Ka e tlogetse dibofo tsa yone, ee, ke gone.", "Ka e tlogetse dibofo tsa yone, ee, ke gone.", "Roboto ya gago go bolelwa fa e le seaparo sa gago Roboto ya gago go bolelwa fa e le seaparo sa gago Roboto ya gago go bolelwa fa e le seaparo sa gago Kouadio Vote e tla bo e le mo seemong se se gaisang mme Kouadio Vote e tla bo e le mo seemong se se gaisang mme Kouadio Vote e tla bo e le mo seemong se se gaisang mme Yo mongwe, boitumelo jo bo bonako, o mo seemong se se maswe thata.", "Yo mongwe, boitumelo jo bo bonako, o mo seemong se se maswe thata.", "Yo mongwe, boitumelo jo bo bonako, o mo seemong se se maswe thata.", "kgotsa mebala ka bonako thata Guinea kgotsa mebala ka bonako thata Guinea kgotsa mebala ka bonako thata Guinea kholera e ne e se se ba neng ba tlile go se dira kholera e ne e se se ba neng ba tlile go se dira kholera e ne e se se ba neng ba tlile go se dira Roland sekoloto kwa Damaseko, ga go na tshenyo mo Roland sekoloto kwa Damaseko, ga go na tshenyo mo Roland sekoloto kwa Damaseko, ga go na tshenyo mo di-bolero tsa matlapa tse dintsintsi, iPhone ya 6 ka ka kgotsa e bopilwe jaaka moriti kgotsa e bopilwe jaaka moriti kgotsa e bopilwe jaaka moriti Ke eo roboto e ka akkuzu, ke wena Ke eo roboto e ka akkuzu, ke wena Ke eo roboto e ka akkuzu, ke wena e nnye go feta bagale ba go feela kwa e nnye go feta bagale ba go feela kwa e nnye go feta bagale ba go feela kwa Diradio le inthanete Diradio le inthanete Diradio le inthanete Diakhaby ba ne ba bogisiwa kwa Perl, morago ga moo Diakhaby ba ne ba bogisiwa kwa Perl, morago ga moo Diakhaby ba ne ba bogisiwa kwa Perl, morago ga moo rolara e e kgonang go kgomiwa mo hoki rolara e e kgonang go kgomiwa mo hoki rolara e e kgonang go kgomiwa mo hoki tse dinnye le tse di rentiwang go umaka di le mmalwa fela tse dinnye le tse di rentiwang go umaka di le mmalwa fela tse dinnye le tse di rentiwang go umaka di le mmalwa fela Malapa a a tshwanang le Simon a tlhophetswe Malapa a a tshwanang le Simon a tlhophetswe Malapa a a tshwanang le Simon a tlhophetswe seabe le lepodise la selotlolo seabe le lepodise la selotlolo seabe le lepodise la selotlolo mosedi o kopa dikatso 3 ka mosedi o kopa dikatso 3 ka mosedi o kopa dikatso 3 ka Tibet [Mmino] [Mmino] [Mmino] mo mo mo mo"], "transcript": [{"start": 3.61, "end": 6.63, "text": "nna"}, {"start": 6.64, "end": 12.42, "text": "ka gonne go ya ka Rre Thibault Salomé wa kwa Morocco"}, {"start": 12.42, "end": 12.43, "text": "ka gonne go ya ka Rre Thibault Salomé wa kwa Morocco"}, {"start": 12.43, "end": 30.939, "text": "ka gonne go ya ka Rre Thibault Salomé wa kwa Morocco ka nako eo Kalinka a neng a simolola letshwaokgwebo la gagwe la Alice"}, {"start": 30.939, "end": 30.949, "text": "ka nako eo Kalinka a neng a simolola letshwaokgwebo la gagwe la Alice"}, {"start": 30.949, "end": 34.09, "text": "ka nako eo Kalinka a neng a simolola letshwaokgwebo la gagwe la Alice Lerois 100 le matshosetsi a bona le Melissa"}, {"start": 34.09, "end": 34.1, "text": "Lerois 100 le matshosetsi a bona le Melissa"}, {"start": 34.1, "end": 37.299, "text": "Lerois 100 le matshosetsi a bona le Melissa Dikhamera tsa maemo a Bollywood tse di nang le"}, {"start": 37.299, "end": 37.309, "text": "Dikhamera tsa maemo a Bollywood tse di nang le"}, {"start": 37.309, "end": 39.93, "text": "Dikhamera tsa maemo a Bollywood tse di nang le Mesese ya satin e tla go dira gore o se ka wa nna"}, {"start": 39.93, "end": 39.94, "text": "Mesese ya satin e tla go dira gore o se ka wa nna"}, {"start": 39.94, "end": 43.319, "text": "Mesese ya satin e tla go dira gore o se ka wa nna dikarolo tsa nomoro ya bone tse a neng a sa di itse"}, {"start": 43.319, "end": 43.329, "text": "dikarolo tsa nomoro ya bone tse a neng a sa di itse"}, {"start": 43.329, "end": 48.31, "text": "dikarolo tsa nomoro ya bone tse a neng a sa di itse ya retina ka gonne motho o na le ditlhabi tsa belimumab"}, {"start": 48.32, "end": 50.67, "text": "[Mmino]"}, {"start": 50.67, "end": 50.68, "text": "[Mmino]"}, {"start": 50.68, "end": 56.38, "text": "[Mmino] le dikgwedi tsa selemo direto tsa Segerika le"}, {"start": 56.38, "end": 56.39, "text": "le dikgwedi tsa selemo direto tsa Segerika le"}, {"start": 56.39, "end": 58.389, "text": "le dikgwedi tsa selemo direto tsa Segerika le difouno tsa selula tse di tlhakanetsweng ntlo ya kago e"}, {"start": 58.389, "end": 58.399, "text": "difouno tsa selula tse di tlhakanetsweng ntlo ya kago e"}, {"start": 58.399, "end": 70.62, "text": "difouno tsa selula tse di tlhakanetsweng ntlo ya kago e go bonala gore lefoko 61st credit go"}, {"start": 70.63, "end": 75.85, "text": "canada ka gonne vuelta cam e mmaagwe perela e nang le yone"}, {"start": 75.85, "end": 75.86, "text": "canada ka gonne vuelta cam e mmaagwe perela e nang le yone"}, {"start": 75.86, "end": 78.73, "text": "canada ka gonne vuelta cam e mmaagwe perela e nang le yone Ka e tlogetse dibofo tsa yone, ee, ke gone."}, {"start": 78.73, "end": 78.74, "text": "Ka e tlogetse dibofo tsa yone, ee, ke gone."}, {"start": 78.74, "end": 80.919, "text": "Ka e tlogetse dibofo tsa yone, ee, ke gone. Roboto ya gago go bolelwa fa e le seaparo sa gago"}, {"start": 80.919, "end": 80.929, "text": "Roboto ya gago go bolelwa fa e le seaparo sa gago"}, {"start": 80.929, "end": 82.809, "text": "Roboto ya gago go bolelwa fa e le seaparo sa gago Kouadio Vote e tla bo e le mo seemong se se gaisang mme"}, {"start": 82.809, "end": 82.819, "text": "Kouadio Vote e tla bo e le mo seemong se se gaisang mme"}, {"start": 82.819, "end": 85.33, "text": "Kouadio Vote e tla bo e le mo seemong se se gaisang mme Yo mongwe, boitumelo jo bo bonako, o mo seemong se se maswe thata."}, {"start": 85.33, "end": 85.34, "text": "Yo mongwe, boitumelo jo bo bonako, o mo seemong se se maswe thata."}, {"start": 85.34, "end": 87.4, "text": "Yo mongwe, boitumelo jo bo bonako, o mo seemong se se maswe thata. kgotsa mebala ka bonako thata Guinea"}, {"start": 87.4, "end": 87.41, "text": "kgotsa mebala ka bonako thata Guinea"}, {"start": 87.41, "end": 89.529, "text": "kgotsa mebala ka bonako thata Guinea kholera e ne e se se ba neng ba tlile go se dira"}, {"start": 89.529, "end": 89.539, "text": "kholera e ne e se se ba neng ba tlile go se dira"}, {"start": 89.539, "end": 92.949, "text": "kholera e ne e se se ba neng ba tlile go se dira Roland sekoloto kwa Damaseko, ga go na tshenyo mo"}, {"start": 92.949, "end": 92.959, "text": "Roland sekoloto kwa Damaseko, ga go na tshenyo mo"}, {"start": 92.959, "end": 100.83, "text": "Roland sekoloto kwa Damaseko, ga go na tshenyo mo di-bolero tsa matlapa tse dintsintsi, iPhone ya 6"}, {"start": 100.84, "end": 103.13, "text": "ka"}, {"start": 103.13, "end": 107.78999999999999, "text": "ka"}, {"start": 107.8, "end": 109.53, "text": "kgotsa e bopilwe jaaka moriti"}, {"start": 109.53, "end": 109.53999999999999, "text": "kgotsa e bopilwe jaaka moriti"}, {"start": 109.53999999999999, "end": 114.15, "text": "kgotsa e bopilwe jaaka moriti Ke eo roboto e ka akkuzu, ke wena"}, {"start": 114.15, "end": 114.16, "text": "Ke eo roboto e ka akkuzu, ke wena"}, {"start": 114.16, "end": 116.13, "text": "Ke eo roboto e ka akkuzu, ke wena e nnye go feta bagale ba go feela kwa"}, {"start": 116.13, "end": 116.14, "text": "e nnye go feta bagale ba go feela kwa"}, {"start": 116.14, "end": 119.85, "text": "e nnye go feta bagale ba go feela kwa Diradio le inthanete"}, {"start": 119.85, "end": 119.86, "text": "Diradio le inthanete"}, {"start": 119.86, "end": 122.46, "text": "Diradio le inthanete Diakhaby ba ne ba bogisiwa kwa Perl, morago ga moo"}, {"start": 122.46, "end": 122.47, "text": "Diakhaby ba ne ba bogisiwa kwa Perl, morago ga moo"}, {"start": 122.47, "end": 125.67, "text": "Diakhaby ba ne ba bogisiwa kwa Perl, morago ga moo rolara e e kgonang go kgomiwa mo hoki"}, {"start": 125.67, "end": 125.68, "text": "rolara e e kgonang go kgomiwa mo hoki"}, {"start": 125.68, "end": 128.04, "text": "rolara e e kgonang go kgomiwa mo hoki tse dinnye le tse di rentiwang go umaka di le mmalwa fela"}, {"start": 128.04, "end": 128.05, "text": "tse dinnye le tse di rentiwang go umaka di le mmalwa fela"}, {"start": 128.05, "end": 129.63, "text": "tse dinnye le tse di rentiwang go umaka di le mmalwa fela Malapa a a tshwanang le Simon a tlhophetswe"}, {"start": 129.63, "end": 129.64, "text": "Malapa a a tshwanang le Simon a tlhophetswe"}, {"start": 129.64, "end": 130.74, "text": "Malapa a a tshwanang le Simon a tlhophetswe seabe le lepodise la selotlolo"}, {"start": 130.74, "end": 130.75, "text": "seabe le lepodise la selotlolo"}, {"start": 130.75, "end": 133.95, "text": "seabe le lepodise la selotlolo mosedi o kopa dikatso 3 ka"}, {"start": 133.95, "end": 133.96, "text": "mosedi o kopa dikatso 3 ka"}, {"start": 133.96, "end": 139.28, "text": "mosedi o kopa dikatso 3 ka Tibet"}, {"start": 139.29, "end": 143.44, "text": "[Mmino]"}, {"start": 143.44, "end": 143.45, "text": "[Mmino]"}, {"start": 143.45, "end": 145.05, "text": "[Mmino] mo"}, {"start": 145.05, "end": 145.06, "text": "mo"}, {"start": 145.06, "end": 147.48, "text": "mo mo"}], "createdAt": "2025-12-15T18:38:58.000Z", "imageUrl": "https://i.ytimg.com/vi_webp/6O511LzRyf8/hqdefault.webp", "type": "audio", "videoUrl": "https://youtube.com/watch?v=6O511LzRyf8", "difficulty": "beginner", "genre": "poetry", "isFavorite": false, "progress": 0}]